python_sample_package_with_data/__init__.py
python_sample_package_with_data/mydata.txt
python_sample_package_with_data-0.0.2.data/scripts/python-sample-package-with-data
python_sample_package_with_data-0.0.2.dist-info/METADATA
python_sample_package_with_data-0.0.2.dist-info/WHEEL
python_sample_package_with_data-0.0.2.dist-info/top_level.txt
python_sample_package_with_data-0.0.2.dist-info/RECORD
