Metadata-Version: 2.1
Name: python-sample-package-with-data
Version: 0.0.2
Summary: My short description
Home-page: https://github.com/cirosantilli/python-sample-package-with-data
Author: Ciro Santilli
Author-email: ciro.santilli.contact@gmail.com
License: UNKNOWN
Platform: UNKNOWN
